geo_optimizer/GEO.py
geo_optimizer/__init__.py
geo_optimizer-1.1.2.dist-info/METADATA
geo_optimizer-1.1.2.dist-info/WHEEL
geo_optimizer-1.1.2.dist-info/top_level.txt
geo_optimizer-1.1.2.dist-info/RECORD
