Metadata-Version: 2.1
Name: geo-optimizer
Version: 1.1.2
Summary: GEO: Genetic & Evolutionary Optimizer — A Neural Network Training framework.
Author: MrPsyghost (Shivay)
Author-email: shivaypuri2000@gmail.com
Project-URL: YouTube, https://www.youtube.com/@MrPsyghost
Keywords: neural networks,evolution,optimizer,genetic algorithm,deep learning,pytorch,neuroevolution,geo
Classifier: Development Status :: 4 - Beta
Classifier: Intended Audience :: Science/Research
Classifier: Topic :: Scientific/Engineering :: Artificial Intelligence
Classifier: Programming Language :: Python :: 3.10
Classifier: Programming Language :: Python :: 3.11
Classifier: Operating System :: OS Independent
Requires-Python: >=3.10
Requires-Dist: torch>=2.0.0
Requires-Dist: matplotlib>=3.10.0
Requires-Dist: rich>=13.0.0
Requires-Dist: tqdm>=4.0.0
